hypeui/__init__.py
hypeui-0.0.dist-info/METADATA
hypeui-0.0.dist-info/WHEEL
hypeui-0.0.dist-info/top_level.txt
hypeui-0.0.dist-info/RECORD
