Metadata-Version: 2.1
Name: hypeui
Version: 0.0
Summary: Coming soon
Author-email: oxynDev <oxyn.dev@gmail.com>
